hiddenfigures/__init__.py
hiddenfigures/command_line.py
hiddenfigures/decompile_replays.py
hiddenfigures/analysis/PROTOBUF_VERSION
hiddenfigures/analysis/__init__.py
hiddenfigures/analysis/analysis_manager.py
hiddenfigures/analysis/cleaner/__init__.py
hiddenfigures/analysis/cleaner/cleaner.py
hiddenfigures/analysis/cleaner/frame_cleaner.py
hiddenfigures/analysis/constants/__init__.py
hiddenfigures/analysis/constants/basic_math.py
hiddenfigures/analysis/constants/dropshot.py
hiddenfigures/analysis/constants/field_constants.py
hiddenfigures/analysis/constants/playlist.py
hiddenfigures/analysis/events/__init__.py
hiddenfigures/analysis/events/carry_detection.py
hiddenfigures/analysis/events/event_creator.py
hiddenfigures/analysis/events/boost_pad_detection/__init__.py
hiddenfigures/analysis/events/boost_pad_detection/pickup_analysis.py
hiddenfigures/analysis/events/bump_detection/__init__.py
hiddenfigures/analysis/events/bump_detection/bump_analysis.py
hiddenfigures/analysis/events/dropshot/__init__.py
hiddenfigures/analysis/events/dropshot/ball.py
hiddenfigures/analysis/events/dropshot/damage.py
hiddenfigures/analysis/events/fifty_fifty/__init__.py
hiddenfigures/analysis/events/fifty_fifty/fifty_analysis.py
hiddenfigures/analysis/events/hit_detection/__init__.py
hiddenfigures/analysis/events/hit_detection/base_hit.py
hiddenfigures/analysis/events/hit_detection/hit_analysis.py
"hiddenfigures/analysis/events/hit_detection/hitbox/Vehicle Specifications v1.39 - Hitboxes, Handling.xlsx"
hiddenfigures/analysis/events/hit_detection/hitbox/__init__.py
hiddenfigures/analysis/events/hit_detection/hitbox/car.py
hiddenfigures/analysis/events/hit_detection/hitbox/hitbox.py
hiddenfigures/analysis/events/hit_pressure/__init__.py
hiddenfigures/analysis/events/hit_pressure/pressure_analysis.py
hiddenfigures/analysis/events/kickoff_detection/__init__.py
hiddenfigures/analysis/events/kickoff_detection/kickoff_analysis.py
hiddenfigures/analysis/saltie_game/__init__.py
hiddenfigures-0.7.11.dist-info/METADATA
hiddenfigures-0.7.11.dist-info/WHEEL
hiddenfigures-0.7.11.dist-info/entry_points.txt
hiddenfigures-0.7.11.dist-info/top_level.txt
hiddenfigures-0.7.11.dist-info/RECORD
