Metadata-Version: 2.1
Name: hiddenfigures
Version: 0.7.11
Summary: Rocket League replay parsing and analysis.
Home-page: https://github.com/millcityrunner/hiddenfigures
Author: Andrew Ray, Corbin Fonville
Author-email: mcaray9@gmail.com
License: Apache 2.0
Keywords: rocket-league
Platform: UNKNOWN
Requires-Dist: pandas (==1.0.3)
Requires-Dist: protobuf (==3.6.1)
Requires-Dist: xlrd (==1.1.0)
Requires-Dist: numpy (==1.18.2)
Requires-Dist: boxcars-py (==0.1.*)
